LICENSE
README.md
stilus/__init__.py
stilus/__version__.py
stilus/cli.py
stilus/colors.py
stilus/exceptions.py
stilus/functions/__init__.py
stilus/functions/addProperty.py
stilus/functions/adjust.py
stilus/functions/alpha.py
stilus/functions/baseConvert.py
stilus/functions/basename.py
stilus/functions/bifs.py
stilus/functions/blend.py
stilus/functions/blue.py
stilus/functions/clone.py
stilus/functions/component.py
stilus/functions/contrast.py
stilus/functions/convert.py
stilus/functions/currentMedia.py
stilus/functions/define.py
stilus/functions/dirname.py
stilus/functions/error.py
stilus/functions/extname.py
stilus/functions/green.py
stilus/functions/hsl.py
stilus/functions/hsla.py
stilus/functions/hue.py
stilus/functions/imageSize.py
stilus/functions/index.styl
stilus/functions/json.py
stilus/functions/length.py
stilus/functions/lightness.py
stilus/functions/listSeparator.py
stilus/functions/lookup.py
stilus/functions/luminosity.py
stilus/functions/match.py
stilus/functions/math.py
stilus/functions/math_prop.py
stilus/functions/merge.py
stilus/functions/operate.py
stilus/functions/oppositePosition.py
stilus/functions/p.py
stilus/functions/pathjoin.py
stilus/functions/pop.py
stilus/functions/prefixClasses.py
stilus/functions/push.py
stilus/functions/range.py
stilus/functions/red.py
stilus/functions/remove.py
stilus/functions/replace.py
stilus/functions/resolver.py
stilus/functions/rgb.py
stilus/functions/rgba.py
stilus/functions/s.py
stilus/functions/saturation.py
stilus/functions/selector.py
stilus/functions/selectorExists.py
stilus/functions/selectors.py
stilus/functions/shift.py
stilus/functions/stilus_slice.py
stilus/functions/stilus_split.py
stilus/functions/substr.py
stilus/functions/tan.py
stilus/functions/trace.py
stilus/functions/transparentify.py
stilus/functions/type_function.py
stilus/functions/unit.py
stilus/functions/unquote.py
stilus/functions/unshift.py
stilus/functions/url.py
stilus/functions/warn.py
stilus/lexer.py
stilus/nodes/__init__.py
stilus-0.9.0.dist-info/entry_points.txt
stilus-0.9.0.dist-info/LICENSE
stilus-0.9.0.dist-info/WHEEL
stilus-0.9.0.dist-info/METADATA
stilus-0.9.0.dist-info/RECORD
