Metadata-Version: 2.1
Name: stilus
Version: 0.9.0
Summary: A Stylus css compiler in Python.
Home-page: https://github.com/jw/stilus
License: GPL-3.0-or-later
Keywords: compiler,stylus,css
Author: Jan Willems
Author-email: jw@elevenbits.com
Maintainer: Jan Willems
Maintainer-email: jw@elevenbits.com
Requires-Python: >=3.6,<4.0
Classifier: License :: OSI Approved :: GNU General Public License v3 or later (GPLv3+)
Classifier: Programming Language :: Python
Classifier: Programming Language :: Python :: 3
Classifier: Programming Language :: Python :: 3.6
Classifier: Programming Language :: Python :: 3.7
Classifier: Programming Language :: Python :: 3.8
Classifier: Programming Language :: Python :: Implementation :: CPython
Requires-Dist: beautifulsoup4
Requires-Dist: click
Requires-Dist: deprecated
Requires-Dist: lxml
Requires-Dist: pillow
Requires-Dist: pyyaml
Requires-Dist: setuptools (>=44.0.0,<45.0.0)
Requires-Dist: watchdog (>=0.8.3,<0.9.0)
Requires-Dist: wheel
Project-URL: Documentation, https://stilus.readthedocs.io/en/latest/
Project-URL: Repository, https://github.com/jw/stilus
